agent.py
initialize.py
models.py
agent_zero_lite-1.0.16.dist-info/licenses/LICENSE
python/__init__.py
python/api/__init__.py
python/api/chat_export.py
python/api/chat_load.py
python/api/chat_remove.py
python/api/chat_reset.py
python/api/csrf_token.py
python/api/ctx_window_get.py
python/api/delete_work_dir_file.py
python/api/download_work_dir_file.py
python/api/file_info.py
python/api/get_work_dir_files.py
python/api/health.py
python/api/import_knowledge.py
python/api/mcp_servers_apply.py
python/api/mcp_servers_status.py
python/api/message.py
python/api/message_async.py
python/api/notification_create.py
python/api/nudge.py
python/api/pause.py
python/api/poll.py
python/api/restart.py
python/api/settings_get.py
python/api/settings_set.py
python/api/tunnel.py
python/api/tunnel_proxy.py
python/api/upload_work_dir_files.py
python/extensions/__init__.py
python/extensions/agent_init/_10_initial_message.py
python/extensions/before_main_llm_call/.gitkeep
python/extensions/before_main_llm_call/_10_log_for_stream.py
python/extensions/message_loop_end/.gitkeep
python/extensions/message_loop_end/_10_organize_history.py
python/extensions/message_loop_end/_90_save_chat.py
python/extensions/message_loop_prompts_after/.gitkeep
python/extensions/message_loop_prompts_after/_50_recall_memories.py
python/extensions/message_loop_prompts_after/_60_include_current_datetime.py
python/extensions/message_loop_prompts_after/_70_include_agent_info.py
python/extensions/message_loop_prompts_after/_91_recall_wait.py
python/extensions/message_loop_prompts_before/.gitkeep
python/extensions/message_loop_prompts_before/_90_organize_history_wait.py
python/extensions/message_loop_start/.gitkeep
python/extensions/message_loop_start/_10_iteration_no.py
python/extensions/monologue_end/.gitkeep
python/extensions/monologue_end/_50_memorize_fragments.py
python/extensions/monologue_end/_51_memorize_solutions.py
python/extensions/monologue_end/_90_waiting_for_input_msg.py
python/extensions/monologue_start/.gitkeep
agent_zero_lite-1.0.16.dist-info/METADATA
agent_zero_lite-1.0.16.dist-info/WHEEL
agent_zero_lite-1.0.16.dist-info/entry_points.txt
agent_zero_lite-1.0.16.dist-info/top_level.txt
agent_zero_lite-1.0.16.dist-info/RECORD
