Metadata-Version: 2.4
Name: agent-zero-lite
Version: 1.0.16
Summary: Lightweight Python AI Agent Framework with Web UI
Home-page: https://github.com/frdel/agent-zero-lite
Author: Agent Zero Community
Author-email: Agent Zero Community <support@agent-zero.io>
Maintainer-email: Agent Zero Community <support@agent-zero.io>
License-Expression: MIT
Project-URL: Homepage, https://github.com/frdel/agent-zero-lite
Project-URL: Documentation, https://github.com/frdel/agent-zero-lite#readme
Project-URL: Repository, https://github.com/frdel/agent-zero-lite
Project-URL: Bug Reports, https://github.com/frdel/agent-zero-lite/issues
Project-URL: Changelog, https://github.com/frdel/agent-zero-lite/blob/main/CHANGELOG.md
Keywords: ai,agent,llm,python,automation,web-ui,litellm,openai,anthropic
Classifier: Development Status :: 4 - Beta
Classifier: Intended Audience :: Developers
Classifier: Operating System :: OS Independent
Classifier: Programming Language :: Python :: 3
Classifier: Programming Language :: Python :: 3.8
Classifier: Programming Language :: Python :: 3.9
Classifier: Programming Language :: Python :: 3.10
Classifier: Programming Language :: Python :: 3.11
Classifier: Programming Language :: Python :: 3.12
Classifier: Topic :: Scientific/Engineering :: Artificial Intelligence
Classifier: Topic :: Software Development :: Libraries :: Python Modules
Requires-Python: >=3.8
License-File: LICENSE
Requires-Dist: aiofiles
Requires-Dist: anthropic
Requires-Dist: beautifulsoup4
Requires-Dist: chromadb
Requires-Dist: cryptography
Requires-Dist: fastapi
Requires-Dist: faiss-cpu>=1.11.0
Requires-Dist: fastmcp>=2.3.4
Requires-Dist: flask[async]>=3.0.3
Requires-Dist: flask-basicauth
Requires-Dist: google-generativeai
Requires-Dist: httpx
Requires-Dist: langchain
Requires-Dist: langchain-community>=0.3.19
Requires-Dist: langchain-core>=0.3.49
Requires-Dist: langchain-openai
Requires-Dist: litellm>=1.74
Requires-Dist: mcp>=1.9.0
Requires-Dist: nest-asyncio
Requires-Dist: numpy
Requires-Dist: openai
Requires-Dist: packaging
Requires-Dist: paramiko>=3.5.0
Requires-Dist: pillow
Requires-Dist: psutil>=7.0.0
Requires-Dist: pydantic
Requires-Dist: python-dotenv>=1.1.0
Requires-Dist: python-multipart
Requires-Dist: pyyaml
Requires-Dist: requests
Requires-Dist: sentence-transformers>=3.0.1
Requires-Dist: simpleeval>=1.0.3
Requires-Dist: tiktoken>=0.8.0
Requires-Dist: uvicorn
Requires-Dist: watchdog
Requires-Dist: webcolors>=24.6.0
Requires-Dist: pytz>=2024.2
Requires-Dist: GitPython>=3.1.43
Requires-Dist: inputimeout>=1.0.4
Requires-Dist: pathspec>=0.12.1
Requires-Dist: a2wsgi>=1.10.8
Requires-Dist: ansio>=0.0.1
Requires-Dist: fasta2a>=0.5.0
Requires-Dist: flaredantic>=0.1.4
Provides-Extra: cpu
Requires-Dist: faiss-cpu>=1.11.0; extra == "cpu"
Requires-Dist: onnxruntime>=1.20.0; extra == "cpu"
Requires-Dist: tiktoken>=0.8.0; extra == "cpu"
Provides-Extra: ml
Requires-Dist: transformers>=4.40.0; extra == "ml"
Requires-Dist: onnxruntime>=1.20.0; extra == "ml"
Provides-Extra: audio
Requires-Dist: openai-whisper>=20240930; extra == "audio"
Provides-Extra: gpu
Requires-Dist: torch>=2.3; extra == "gpu"
Requires-Dist: onnxruntime-gpu>=1.20.0; extra == "gpu"
Requires-Dist: faiss-gpu>=1.11.0; extra == "gpu"
Requires-Dist: triton>=3.0.0; extra == "gpu"
Provides-Extra: dev
Requires-Dist: black>=23.0.0; extra == "dev"
Requires-Dist: isort>=5.12.0; extra == "dev"
Requires-Dist: flake8>=6.0.0; extra == "dev"
Requires-Dist: pytest>=7.4.0; extra == "dev"
Requires-Dist: pytest-asyncio>=0.21.0; extra == "dev"
Provides-Extra: docs
Requires-Dist: mkdocs>=1.5.0; extra == "docs"
Requires-Dist: mkdocs-material>=9.4.0; extra == "docs"
Dynamic: author
Dynamic: home-page
Dynamic: license-file
Dynamic: requires-python
